Workbook

Sheet Sales by Customer Detail
A1: First Arriving LLC
A2: Sales by Customer Detail
A3: January 2018 - April 2022
B5: Customer | C5: Date | D5: Transaction Type | E5: Num | F5: Product/Service | G5: Memo/Description | H5: Account | I5: Class | J5: Qty | K5: Sales Price | L5: Amount | M5: Balance | N5: Subscription Start Date | O5: Subscription End Date
B6: Maryland State Fireman's Assoc | C6: 01/02/2018 | D6: Invoice | E6: 1014 | F6: Strategic Services:Strategic Services | G6: Maryland State Fireman's Association - Recruitment Campaign Marketing Services (January Payment) | H6: 4307 Marketing Services:Marketing Strategy/Ops | J6: 1 | K6: 30000 | L6: 30000 | M6: 30000
B7: National Fallen Firefighters Foundation (MD) | C7: 01/03/2018 | D7: Invoice | E7: 1016 | F7: Website Packages:Hosting & Support:Hosting & Support | G7: September 2017-December 2017 | H7: 4902 Websites:Website Hosting/Support | J7: 4 | K7: 150 | L7: 600 | M7: 30600
B8: APS Firehouse Alerting | C8: 01/03/2018 | D8: Invoice | E8: 1017 | F8: Website Packages:Hosting & Support:Hosting & Support | G8: 10% Annual Discount | H8: 4902 Websites:Website Hosting/Support | J8: 1 | K8: -35 | L8: -35 | M8: 30565
B9: APS Firehouse Alerting | C9: 01/03/2018 | D9: Invoice | E9: 1017 | F9: Website Packages:Hosting & Support:Hosting & Support | G9: 2018 Hosting & Support | H9: 4902 Websites:Website Hosting/Support | J9: 12 | K9: 29 | L9: 348 | M9: 30913
B10: First Class (NC) Emergency Vehicles | C10: 01/03/2018 | D10: Invoice | E10: 1018 | F10: Website Packages:Hosting & Support:Hosting & Support | G10: Hosting & Support for 2018 | H10: 4902 Websites:Website Hosting/Support | J10: 12 | K10: 49 | L10: 588 | M10: 31501
B11: National Fallen Firefighters Foundation (MD) | C11: 01/03/2018 | D11: Invoice | E11: 1016 | F11: Website Packages:Hosting & Support:Hosting & Support | G11: 2018 | H11: 4902 Websites:Website Hosting/Support | J11: 12 | K11: 150 | L11: 1800 | M11: 33301
B12: First Class (NC) Emergency Vehicles | C12: 01/03/2018 | D12: Invoice | E12: 1018 | F12: Website Packages:Hosting & Support:Hosting & Support | G12: Annual Pre-Pay Discount | H12: 4902 Websites:Website Hosting/Support | J12: 1 | K12: -58.8 | L12: -58.8 | M12: 33242.2
B13: National Fallen Firefighters Foundation (MD) | C13: 01/03/2018 | D13: Invoice | E13: 1016 | F13: Website Packages:Hosting & Support:Hosting & Support | G13: 10% Courtesy Discount | H13: 4902 Websites:Website Hosting/Support | J13: 1 | K13: -240 | L13: -240 | M13: 33002.2
B14: South Carolina State Firefighters Association:South Carolina State Firefighter's Association - Recruitment | C14: 01/18/2018 | D14: Invoice | E14: 1019 | F14: Recruitment Services:Recruitment & Retention Strategy & Project Management | G14: SCSFA Recruitment Marketing - Initial Retainer | H14: 4603 Recruitment Services:Recruitment Strategy/Management | J14: 1 | K14: 40000 | L14: 40000 | M14: 73002.2
B15: Bendersville Community (PA) Fire Company | C15: 01/31/2018 | D15: Invoice | E15: 1020 | F15: Website Packages:Hosting & Support:Hosting & Support | G15: Hosting & Support (Package 2 Level) - 2 Years Site Post Launch Date | H15: 4902 Websites:Website Hosting/Support | J15: 24 | K15: 59 | L15: 1416 | M15: 74418.2
B16: Bendersville Community (PA) Fire Company | C16: 01/31/2018 | D16: Invoice | E16: 1020 | F16: Web Services:Website Services | G16: Package 2 - Custom | H16: 4903 Websites:Website Services | J16: 1 | K16: 3495 | L16: 3495 | M16: 77913.2
B17: Round Lake (NY) Hose Company #1 Inc | C17: 01/31/2018 | D17: Invoice | E17: 1021 | F17: Web Services:Website Services | G17: Package 1 + Enhanced Recruitment/Fundraising, QGiv Basic Plan (initially), Review Print Mailer, Custom FB Audiences, 501c3 Setup for Google and Facebook | H17: 4903 Websites:Website Services | J17: 1 | K17: 0 | L17: 0 | M17: 77913.2
B18: Round Lake (NY) Hose Company #1 Inc | C18: 01/31/2018 | D18: Invoice | E18: 1021 | F18: Web Services:Website Services | G18: Package 2 - Custom (Defined Below) | H18: 4903 Websites:Website Services | J18: 1 | K18: 2795 | L18: 2795 | M18: 80708.2
B19: Bendersville Community (PA) Fire Company | C19: 01/31/2018 | D19: Invoice | E19: 1020 | F19: Strategic Services:Strategic Services | G19: Facebook Marketing Pass Through (Two Years) | H19: 4307 Marketing Services:Marketing Strategy/Ops | J19: 1 | K19: 600 | L19: 600 | M19: 81308.2
B20: Bendersville Community (PA) Fire Company | C20: 01/31/2018 | D20: Invoice | E20: 1020 | F20: Strategic Services:Strategic Services | G20: NVFC Member / Courtesy Discount | H20: 4307 Marketing Services:Marketing Strategy/Ops | J20: 1 | K20: -511 | L20: -511 | M20: 80797.2
B21: South Carolina State Firefighters Association:South Carolina State Firefighter's Association - Recruitment | C21: 02/02/2018 | D21: Invoice | E21: 1022 | F21: Strategic Services:Strategic Services | G21: SCSFA Recruitment Marketing Program - February 15 Installment | H21: 4307 Marketing Services:Marketing Strategy/Ops | J21: 1 | K21: 30000 | L21: 30000 | M21: 110797.2
B22: Maryland State Fireman's Assoc | C22: 02/02/2018 | D22: Invoice | E22: 1015 | F22: Strategic Services:Strategic Services | G22: UPDATED - Maryland State Fireman's Association - Recruitment Campaign Marketing Services - February Invoice | H22: 4307 Marketing Services:Marketing Strategy/Ops | J22: 1 | K22: 30000 | L22: 30000 | M22: 140797.2
B23: Providence (MD) Volunteer Fire Co. | C23: 02/20/2018 | D23: Invoice | E23: 1024 | F23: Strategic Services:Strategic Services | G23: Payments on Future Invoices (See Notes Below) | H23: 4307 Marketing Services:Marketing Strategy/Ops | J23: 1 | K23: -2830 | L23: -2830 | M23: 137967.2
... B138: Colmar (PA) Volunteer Fire Co:Colmar (PA) Recruitment | C138: 08/13/2018 | D138: Invoice | E138: 1075 | F138: Website Packages:Hosting & Support:Hosting & Support | G138: First 12 months of Website hosting/support included free, then $59/month, due annually on anniversary date of launch | H138: 4902 Websites:Website Hosting/Support | J138: 1 | K138: 0 | L138: 0 | M138: 458485.02
B139: North Carolina (NC) Fire and Rescue Administrative Professionals, Inc | C139: 08/13/2018 | D139: Invoice | E139: 1074 | F139: Website Packages:Hosting & Support:Hosting & Support | G139: First 12 months of hosting/support included from launch date per Proposal., then $29/month paid annually due on anniversary date of launch. | H139: 4902 Websites:Website Hosting/Support | K139: 0 | L139: 0 | M139: 458485.02
B140: Glacier Park International Airport (MT) Fire Rescue | C140: 08/13/2018 | D140: Invoice | E140: 1076 | F140: Dashboards:Dashboard STANDARD Setup | G140: Pre-Loaded PSIN Chromebit (includes shipping) | H140: 4130 Digital Signage:Dashboard Setup Fees | J140: 1 | K140: 119 | L140: 119 | M140: 458604.02
B141: Praetorian Digital (CA) | C141: 08/16/2018 | D141: Invoice | E141: 1078 | F141: Marketing Services:Marketing Services - Sagetopia (deleted) | G141: Project Includes - Design & Layout - Hyperlinks - Text changes - File preparation for printing | H141: 4304 Marketing Services:Design/Production - Third Party Pass Through | J141: 1 | K141: 0 | L141: 0 | M141: 458604.02
B142: Praetorian Digital (CA) | C142: 08/16/2018 | D142: Invoice | E142: 1078 | F142: Marketing Services:Marketing Services - Sagetopia (deleted) | G142: Stock Images - Female Police Officer | H142: 4304 Marketing Services:Design/Production - Third Party Pass Through | J142: 1 | K142: 12 | L142: 12 | M142: 458616.02
B143: Praetorian Digital (CA) | C143: 08/16/2018 | D143: Invoice | E143: 1077 | F143: Marketing Services:Marketing Services - Sagetopia (deleted) | G143: eBook: Increase Safety and Maximize Resources with Connected Devices and Cloud-based Technology | H143: 4304 Marketing Services:Design/Production - Third Party Pass Through | J143: 1 | K143: 0 | L143: 0 | M143: 458616.02
B144: Praetorian Digital (CA) | C144: 08/16/2018 | D144: Invoice | E144: 1077 | F144: Marketing Services:Marketing Services - Sagetopia (deleted) | G144: eBook Design & Layout (16 pages) - 2 Cover Options - Interior Page Layout - 3 rounds of text edits - Not to exceed 4 hours of text edits - Hyperlinks (TOC, email & web addresses) - Capped at $1750 | H144: 4304 Marketing Services:Design/Production - Third Party Pass Through | J144: 1 | K144: 1750 | L144: 1750 | M144: 460366.02
B145: Praetorian Digital (CA) | C145: 08/16/2018 | D145: Invoice | E145: 1078 | F145: Marketing Services:Marketing Services - Sagetopia (deleted) | G145: Design: Interior Pages | H145: 4304 Marketing Services:Design/Production - Third Party Pass Through | J145: 6 | K145: 175 | L145: 1050 | M145: 461416.02
B146: Praetorian Digital (CA) | C146: 08/16/2018 | D146: Invoice | E146: 1078 | F146: Marketing Services:Marketing Services - Sagetopia (deleted) | G146: Design: Covers | H146: 4304 Marketing Services:Design/Production - Third Party Pass Through | J146: 1 | K146: 300 | L146: 300 | M146: 461716.02
B147: Praetorian Digital (CA) | C147: 08/16/2018 | D147: Invoice | E147: 1078 | F147: Marketing Services:Marketing Services - Sagetopia (deleted) | G147: eBook Design: Kronos / PoliceOne Increase Engagement with Modern Scheduling Technology Total: 7 Pages | H147: 4304 Marketing Services:Design/Production - Third Party Pass Through | J147: 1 | K147: 0 | L147: 0 | M147: 461716.02
B148: Praetorian Digital (CA) | C148: 08/16/2018 | D148: Invoice | E148: 1079 | F148: Marketing Services:Marketing Services - Sagetopia (deleted) | G148: Project Includes - Design & Layout - Hyperlinks - Text changes - File preparation for printing | H148: 4304 Marketing Services:Design/Production - Third Party Pass Through | J148: 1 | K148: 0 | L148: 0 | M148: 461716.02
B149: Praetorian Digital (CA) | C149: 08/16/2018 | D149: Invoice | E149: 1079 | F149: Marketing Services:Marketing Services - Sagetopia (deleted) | G149: Design: Interior Pages | H149: 4304 Marketing Services:Design/Production - Third Party Pass Through | J149: 11 | K149: 175 | L149: 1925 | M149: 463641.02
B150: Praetorian Digital (CA) | C150: 08/16/2018 | D150: Invoice | E150: 1079 | F150: Marketing Services:Marketing Services - Sagetopia (deleted) | G150: Design: Covers | H150: 4304 Marketing Services:Design/Production - Third Party Pass Through | J150: 1 | K150: 300 | L150: 300 | M150: 463941.02
B151: Praetorian Digital (CA) | C151: 08/16/2018 | D151: Invoice | E151: 1079 | F151: Marketing Services:Marketing Services - Sagetopia (deleted) | G151: eBook Design: Kyocera / PoliceOne What Agencies need to know about: BWC-ENABLED SMARTPHONES Total: 12 Pages | H151: 4304 Marketing Services:Design/Production - Third Party Pass Through | J151: 1 | K151: 0 | L151: 0 | M151: 463941.02
... B429: Interstate Rescue (VA) | C429: 01/01/2019 | D429: Invoice | E429: 1233 | F429: Strategic Services:Strategic Services | G429: Regional Marketing Program - Setup per proposal 12/26 | H429: 4307 Marketing Services:Marketing Strategy/Ops | J429: 1 | K429: 1000 | L429: 1000 | M429: 1178294.6
B430: Branchville (MD) Volunteer Fire Company and Rescue Squad, Inc | C430: 01/02/2019 | D430: Invoice | E430: 1234 | F430: Dashboards:Dashboard - Hardware (deleted) | G430: Chromebit for additional dashboard | H430: 4700 Strategic Services | J430: 0 | L430: 0 | M430: 1178294.6
B431: Haltom City (TX) Fire Department | C431: 01/03/2019 | D431: Invoice | E431: 1235 | F431: Dashboards:Dashboard STANDARD Setup | G431: PSIN Implementation Fee for 3 locations | H431: 4130 Digital Signage:Dashboard Setup Fees | J431: 1 | K431: 795 | L431: 795 | M431: 1179089.6
B432: Haltom City (TX) Fire Department | C432: 01/03/2019 | D432: Invoice | E432: 1235 | F432: Dashboards:Dashboard - First Year New Standard License (LEGACY) (deleted) | G432: Annual Licenses for PSIN Service (renews annually due on anniversary of deployment) | H432: 4110 Digital Signage:Dashboard Licenses | J432: 4 | K432: 349 | L432: 1396 | M432: 1180485.6
B433: Haltom City (TX) Fire Department | C433: 01/03/2019 | D433: Invoice | E433: 1235 | F433: Dashboards:Dashboard - Hardware Device Deployment | G433: Pre-Loaded Chromebit with PSIN Services (including shipping) | H433: 4103 Digital Signage:Dashboard Hardware/Deployment | J433: 4 | K433: 119 | L433: 476 | M433: 1180961.6
B434: Greenfield (WI) Fire Department, City of | C434: 01/04/2019 | D434: Invoice | E434: 1236 | F434: Dashboards:Dashboard - First Year New Standard License (LEGACY) (deleted) | G434: Pro-rated additional licenses | H434: 4110 Digital Signage:Dashboard Licenses | J434: 2 | K434: 273 | L434: 546 | M434: 1181507.6
B435: Greenfield (WI) Fire Department, City of | C435: 01/04/2019 | D435: Invoice | E435: 1236 | F435: Dashboards:Dashboard - Hardware Device Deployment | G435: Chromebit media players | H435: 4103 Digital Signage:Dashboard Hardware/Deployment | J435: 2 | K435: 119 | L435: 238 | M435: 1181745.6
B436: Hillside (NJ) Fire Department | C436: 01/05/2019 | D436: Invoice | E436: 1197 | F436: Dashboards:Dashboard Renewal - Annual License Renewal - PSIN Launch Client | G436: First Arriving (PSIN) Annual License Fee (2/1/19-1/31/20) | H436: 4110 Digital Signage:Dashboard Licenses | J436: 1 | K436: 492 | L436: 492 | M436: 1182237.6
B437: Longview (WA) Fire Department | C437: 01/05/2019 | D437: Invoice | E437: 1198 | F437: Dashboards:Dashboard Renewal - Annual License Renewal - PSIN Launch Client | G437: First Arriving (PSIN) Annual License Fee (2/1/19-1/31/20) | H437: 4110 Digital Signage:Dashboard Licenses | J437: 7 | K437: 259 | L437: 1813 | M437: 1184050.6
B438: Felicity Franklin (OH) Fire Department | C438: 01/05/2019 | D438: Invoice | E438: 1208 | F438: Dashboards:Dashboard Renewal - Annual License Renewal - PSIN Launch Client | G438: First Arriving (PSIN) Annual License Fee (2/15/19-2/14/20) | H438: 4110 Digital Signage:Dashboard Licenses | J438: 1 | K438: 399 | L438: 399 | M438: 1184449.6
B439: Mountain Home (NC) Fire & Rescue | C439: 01/05/2019 | D439: Invoice | E439: 1209 | F439: Dashboards:Dashboard Renewal - Annual License Renewal - PSIN Launch Client | G439: First Arriving (PSIN) Annual License Fee (2/15/19-2/14/20) | H439: 4110 Digital Signage:Dashboard Licenses | J439: 2 | K439: 359 | L439: 718 | M439: 1185167.6
B440: Country Club Hills (IL) Fire Department | C440: 01/05/2019 | D440: Invoice | E440: 1195 | F440: Dashboards:Dashboard Renewal - Annual License Renewal - PSIN Launch Client | G440: First Arriving (PSIN) Annual License Fee (2/1/19-1/31/20) - Revised License Cost | H440: 4110 Digital Signage:Dashboard Licenses | J440: 7 | K440: 259 | L440: 1813 | M440: 1186980.6
B441: Troutville (VA) Fire Department | C441: 01/05/2019 | D441: Invoice | E441: 1210 | F441: Dashboards:Dashboard Renewal - Annual License Renewal - PSIN Launch Client | G441: First Arriving (PSIN) Annual License Fee (2/15/19-2/14/20) | H441: 4110 Digital Signage:Dashboard Licenses | J441: 2 | K441: 259 | L441: 518 | M441: 1187498.6
B442: Glacier Park International Airport (MT) Fire Rescue | C442: 01/05/2019 | D442: Invoice | E442: 1196 | F442: Dashboards:Dashboard Renewal - Annual License Renewal - PSIN Launch Client | G442: First Arriving (PSIN) Annual License Fee (2/1/19-1/31/20) | H442: 4110 Digital Signage:Dashboard Licenses | J442: 7 | K442: 185 | L442: 1295 | M442: 1188793.6
... B447: South Lake Tahoe (CA) Fire Dept | C447: 01/12/2019 | D447: Invoice | E447: 1241 | F447: Dashboards:Dashboard - First Year New Standard License (LEGACY) (deleted) | G447: Annual Licenses for PSIN Service (renews annually due on anniversary of deployment) | H447: 4110 Digital Signage:Dashboard Licenses | J447: 4 | K447: 349 | L447: 1396 | M447: 1202401.6
B448: Oconee County (SC) Emergency Services | C448: 01/12/2019 | D448: Invoice | E448: 1240 | F448: Dashboards:Dashboard - First Year New Standard License (LEGACY) (deleted) | G448: Annual Licenses for PSIN Service (renews annually due on anniversary of deployment) | H448: 4110 Digital Signage:Dashboard Licenses | J448: 0 | L448: 0 | M448: 1202401.6
B449: Blacksburg (VA) Volunteer Rescue Squad | C449: 01/12/2019 | D449: Invoice | E449: 1239 | F449: Dashboards:Dashboard - First Year New Standard License (LEGACY) (deleted) | G449: Annual Licenses for PSIN Service (renews annually due on anniversary of deployment) | H449: 4110 Digital Signage:Dashboard Licenses | J449: 3 | K449: 349 | L449: 1047 | M449: 1203448.6
B450: Sunrise Beach (MO) Fire Protection District | C450: 01/12/2019 | D450: Invoice | E450: 1245 | F450: Dashboards:Dashboard - Hardware Device Deployment | G450: Pre-Loaded Chromebit with PSIN Services (including shipping) | H450: 4103 Digital Signage:Dashboard Hardware/Deployment | J450: 3 | K450: 119 | L450: 357 | M450: 1203805.6
B451: Lake Ozark (MO) Fire Protection District | C451: 01/12/2019 | D451: Invoice | E451: 1244 | F451: Dashboards:Dashboard - Hardware Device Deployment | G451: Pre-Loaded Chromebit with PSIN Services (including shipping) | H451: 4103 Digital Signage:Dashboard Hardware/Deployment | J451: 4 | K451: 119 | L451: 476 | M451: 1204281.6
B452: Bellevue-Dayton (KY) Fire Department | C452: 01/12/2019 | D452: Invoice | E452: 1242 | F452: Dashboards:Dashboard - Hardware Device Deployment | G452: Pre-Loaded Chromebit with PSIN Services (including shipping) | H452: 4103 Digital Signage:Dashboard Hardware/Deployment | J452: 1 | K452: 119 | L452: 119 | M452: 1204400.6
B453: South Lake Tahoe (CA) Fire Dept | C453: 01/12/2019 | D453: Invoice | E453: 1241 | F453: Dashboards:Dashboard - Hardware Device Deployment | G453: Pre-Loaded Chromebit with PSIN Services (including shipping) | H453: 4103 Digital Signage:Dashboard Hardware/Deployment | J453: 4 | K453: 119 | L453: 476 | M453: 1204876.6
B454: Oconee County (SC) Emergency Services | C454: 01/12/2019 | D454: Invoice | E454: 1240 | F454: Dashboards:Dashboard - Hardware Device Deployment | G454: Pre-Loaded Chromebit with PSIN Services (including shipping) | H454: 4103 Digital Signage:Dashboard Hardware/Deployment | J454: 0 | L454: 0 | M454: 1204876.6
B455: Blacksburg (VA) Volunteer Rescue Squad | C455: 01/12/2019 | D455: Invoice | E455: 1239 | F455: Dashboards:Dashboard - Hardware Device Deployment | G455: Pre-Loaded Chromebit with PSIN Services (including shipping) | H455: 4103 Digital Signage:Dashboard Hardware/Deployment | J455: 3 | K455: 119 | L455: 357 | M455: 1205233.6
B456: Sunrise Beach (MO) Fire Protection District | C456: 01/12/2019 | D456: Invoice | E456: 1245 | F456: Dashboards:Dashboard Custom Setup / Services (deleted) | G456: PSIN Implementation Fee | H456: 4102 Digital Signage:Custom Development | J456: 1 | K456: 500 | L456: 500 | M456: 1205733.6
B457: Lake Ozark (MO) Fire Protection District | C457: 01/12/2019 | D457: Invoice | E457: 1244 | F457: Dashboards:Dashboard Custom Setup / Services (deleted) | G457: PSIN Implementation Fee | H457: 4102 Digital Signage:Custom Development | J457: 1 | K457: 500 | L457: 500 | M457: 1206233.6
B458: Bellevue-Dayton (KY) Fire Department | C458: 01/12/2019 | D458: Invoice | E458: 1242 | F458: Dashboards:Dashboard Custom Setup / Services (deleted) | G458: PSIN Implementation Fee | H458: 4102 Digital Signage:Custom Development | J458: 1 | K458: 595 | L458: 595 | M458: 1206828.6
B459: South Lake Tahoe (CA) Fire Dept | C459: 01/12/2019 | D459: Invoice | E459: 1241 | F459: Dashboards:Dashboard Custom Setup / Services (deleted) | G459: PSIN Implementation Fee | H459: 4102 Digital Signage:Custom Development | J459: 1 | K459: 795 | L459: 795 | M459: 1207623.6
B460: Oconee County (SC) Emergency Services | C460: 01/12/2019 | D460: Invoice | E460: 1240 | F460: Dashboards:Dashboard Custom Setup / Services (deleted) | G460: PSIN Implementation Fee | H460: 4102 Digital Signage:Custom Development | J460: 0 | L460: 0 | M460: 1207623.6
B461: Blacksburg (VA) Volunteer Rescue Squad | C461: 01/12/2019 | D461: Invoice | E461: 1239 | F461: Dashboards:Dashboard Custom Setup / Services (deleted) | G461: PSIN Implementation Fee | H461: 4102 Digital Signage:Custom Development | J461: 1 | K461: 595 | L461: 595 | M461: 1208218.6
B462: Sunrise Beach (MO) Fire Protection District | C462: 01/12/2019 | D462: Invoice | E462: 1245 | F462: Dashboards:Dashboard - First Year New Standard License (LEGACY) (deleted) | G462: Annual Licenses for PSIN Service (renews annually due on anniversary of deployment) | H462: 4110 Digital Signage:Dashboard Licenses | J462: 3 | K462: 349 | L462: 1047 | M462: 1209265.6
B463: Lake Ozark (MO) Fire Protection District | C463: 01/12/2019 | D463: Invoice | E463: 1244 | F463: Dashboards:Dashboard - First Year New Standard License (LEGACY) (deleted) | G463: Annual Licenses for PSIN Service (renews annually due on anniversary of deployment) | H463: 4110 Digital Signage:Dashboard Licenses | J463: 4 | K463: 349 | L463: 1396 | M463: 1210661.6
B464: University of Alaska Fairbanks (AK) Fire Department | C464: 01/15/2019 | D464: Invoice | E464: 1247 | F464: Dashboards:Dashboard - First Year New Standard License (LEGACY) (deleted) | G464: Additional License pro-rated from 1/15/2019 until 4/1/19 (which is the renewal date) | H464: 4110 Digital Signage:Dashboard Licenses | J464: 1 | K464: 141 | L464: 141 | M464: 1210802.6
B465: Go Forward Media, LLC | C465: 01/16/2019 | D465: Invoice | E465: 1248 | F465: Strategic Services:Strategic Services | G465: Consulting services for Paratech - January (Pass Through) | H465: 4307 Marketing Services:Marketing Strategy/Ops | J465: 1 | K465: 10000 | L465: 10000 | M465: 1220802.6
B466: GearGrid Corporation (MN) | C466: 01/18/2019 | D466: Invoice | E466: 1246 | F466: Strategic Services:Strategic Services | G466: Marketing Services for upcoming month including ongoing SEO Management, marketing campaign strategy/recommendations, implementation and management of Google and/or Facebook/social media marketing programs, monthly traffic & marketing ROI tracking, website hosting and support | H466: 4307 Marketing Services:Marketing Strategy/Ops | J466: 1 | K466: 2500 | L466: 2500 | M466: 1223302.6
B467: William Goldfeder (Loveland Personal Displays) (OH) | C467: 01/18/2019 | D467: Invoice | E467: 1249 | F467: Dashboards:Dashboard - Hardware Device Deployment | G467: Four Chromebit Devices, pre-loaded | H467: 4103 Digital Signage:Dashboard Hardware/Deployment | J467: 1 | K467: 119 | L467: 119 | M467: 1223421.6
B468: Loveland-Symmes (OH) Fire Department:Symmes Township (OH) Fire Division | C468: 01/18/2019 | D468: Invoice | E468: 1250 | F468: Dashboards:Dashboard - Hardware Device Deployment | G468: Pre-Loaded Chromsbits for Dashboard deployments, including shipping | H468: 4103 Digital Signage:Dashboard Hardware/Deployment | J468: 2.5 | K468: 119 | L468: 297.5 | M468: 1223719.1
B469: William Goldfeder (Loveland Personal Displays) (OH) | C469: 01/18/2019 | D469: Invoice | E469: 1249 | F469: Dashboards:Dashboard STANDARD Setup | G469: Setup services included in department agreement | H469: 4130 Digital Signage:Dashboard Setup Fees | J469: 1 | K469: 0 | L469: 0 | M469: 1223719.1
B470: William Goldfeder (Loveland Personal Displays) (OH) | C470: 01/18/2019 | D470: Invoice | E470: 1249 | F470: Dashboards:Dashboard - First Year New Standard License (LEGACY) (deleted) | G470: Annual Dashboard Display (Loveland-Symmes Fire Department), discounted courtesy rate for in-home displays, renewal date will be one year from Activation | H470: 4110 Digital Signage:Dashboard Licenses | J470: 1 | K470: 249 | L470: 249 | M470: 1223968.1
B471: Loveland-Symmes (OH) Fire Department:Symmes Township (OH) Fire Division | C471: 01/18/2019 | D471: Invoice | E471: 1250 | F471: Dashboards:Dashboard - First Year New Standard License (LEGACY) (deleted) | G471: Annual license for paid Dashboard, discounted. Additional future devices $299/annually. Renewal date one year from activation. | H471: 4110 Digital Signage:Dashboard Licenses | J471: 0.5 | K471: 299 | L471: 149.5 | M471: 1224117.6
B472: Belgium Cold Springs (NY) Fire Department | C472: 01/18/2019 | D472: Invoice | E472: 1251 | F472: Web Services:Website Services | G472: Website Package 2 in Solutions Guide, discounted. Hosting/Support renews on one year anniversary of website LAUNCH date. | H472: 4903 Websites:Website Services | J472: 1 | K472: 3145 | L472: 3145 | M472: 1227262.6
... B754: Mobile (AL) Fire-Rescue Department, City of | C754: 05/13/2019 | D754: Invoice | E754: 1361 | F754: Dashboards:Dashboard - First Year New Standard License (LEGACY) (deleted) | G754: First Arriving Dashboards annual license, 2+ license, renews on one-year anniversary of deployment | H754: 4110 Digital Signage:Dashboard Licenses | J754: 19 | K754: 339 | L754: 6441 | M754: 1740295.7
B755: Riverdale Heights (MD) Volunteer Fire Department:Riverdale Heights (MD) Project | C755: 05/13/2019 | D755: Invoice | E755: 1362 | F755: Recruitment Services:Recruitment Marketing & Campaign Management | G755: Recruitment marketing | H755: 4601 Recruitment Services:Marketing - Recruitment | J755: 0 | L755: 0 | M755: 1740295.7
B756: Mobile (AL) Fire-Rescue Department, City of | C756: 05/13/2019 | D756: Invoice | E756: 1361 | F756: Dashboards:Dashboard - Hardware Device Deployment | G756: Chromebit, pre-loaded including shipping | H756: 4103 Digital Signage:Dashboard Hardware/Deployment | J756: 19 | K756: 119 | L756: 2261 | M756: 1742556.7
B757: Mobile (AL) Fire-Rescue Department, City of | C757: 05/13/2019 | D757: Invoice | E757: 1361 | F757: Dashboards:Dashboard STANDARD Setup | G757: Agency setup (including first location), discounted | H757: 4130 Digital Signage:Dashboard Setup Fees | J757: 1 | K757: 525 | L757: 525 | M757: 1743081.7
B758: Mobile (AL) Fire-Rescue Department, City of | C758: 05/13/2019 | D758: Invoice | E758: 1361 | F758: Dashboards:Dashboard STANDARD Setup | G758: Per Station Dashboard setup, discounted from $99/each | H758: 4130 Digital Signage:Dashboard Setup Fees | J758: 18 | K758: 79 | L758: 1422 | M758: 1744503.7
B759: Kimball Township (MI) Fire Department | C759: 05/14/2019 | D759: Invoice | E759: 1368 | F759: Dashboards:Dashboard - Hardware Device Deployment | G759: Pre-Loaded Chromebit with First Arriving Dashboard services (including shipping) | H759: 4103 Digital Signage:Dashboard Hardware/Deployment | J759: 1 | K759: 214 | L759: 214 | M759: 1744717.7
B760: Mountain Home (NC) Fire & Rescue:Mountain Home (NC) Fire & Rescue Website | C760: 05/14/2019 | D760: Invoice | E760: 1363 | F760: Web Services:Website Services | G760: First Arriving Website Package 1 - Dashboard Customer Discount (normally $1,895) | H760: 4903 Websites:Website Services | J760: 1 | K760: 1695 | L760: 1695 | M760: 1746412.7
B761: Bedford (OH) Fire Department, City of | C761: 05/14/2019 | D761: Invoice | E761: 1366 | F761: Dashboards:Dashboard - Hardware Device Deployment | G761: Pre-Loaded Chromebit with First Arriving Dashboard services (including shipping) | H761: 4103 Digital Signage:Dashboard Hardware/Deployment | J761: 1 | K761: 119 | L761: 119 | M761: 1746531.7
B762: Palm Beach (FL), Town of | C762: 05/14/2019 | D762: Invoice | E762: 1365 | F762: Dashboards:Dashboard - Hardware Device Deployment | G762: Pre-Loaded Chromebit (including shipping) | H762: 4103 Digital Signage:Dashboard Hardware/Deployment | J762: 1 | K762: 119 | L762: 119 | M762: 1746650.7
B763: Westlake (OH) Fire Department:City of Westlake (OH) Finance Department | C763: 05/14/2019 | D763: Invoice | E763: 1364 | F763: Dashboards:Dashboard - Hardware Device Deployment | G763: Pre-Loaded Chromebit with PSIN Services (including shipping) | H763: 4103 Digital Signage:Dashboard Hardware/Deployment | J763: 4 | K763: 119 | L763: 476 | M763: 1747126.7
B764: Kimball Township (MI) Fire Department | C764: 05/14/2019 | D764: Invoice | E764: 1369 | F764: Dashboards:Dashboard - First Year New Standard License (LEGACY) (deleted) | G764: Annual Licenses for First Arriving Dashboard Service (renews annually due on anniversary of deployment) | H764: 4110 Digital Signage:Dashboard Licenses | J764: 1 | K764: 399 | L764: 399 | M764: 1747525.7
B765: Bedford (OH) Fire Department, City of | C765: 05/14/2019 | D765: Invoice | E765: 1366 | F765: Dashboards:Dashboard - First Year New Standard License (LEGACY) (deleted) | G765: Annual Licenses for First Arriving Dashboard Service (renews annually due on anniversary of deployment) | H765: 4110 Digital Signage:Dashboard Licenses | J765: 1 | K765: 399 | L765: 399 | M765: 1747924.7
B766: Westlake (OH) Fire Department:City of Westlake (OH) Finance Department | C766: 05/14/2019 | D766: Invoice | E766: 1364 | F766: Dashboards:Dashboard - First Year New Standard License (LEGACY) (deleted) | G766: Annual Licenses for First Arriving Dashboard Service (renews annually due on anniversary of deployment) | H766: 4110 Digital Signage:Dashboard Licenses | J766: 4 | K766: 349 | L766: 1396 | M766: 1749320.7
B767: Palm Beach (FL), Town of | C767: 05/14/2019 | D767: Invoice | E767: 1365 | F767: Dashboards:Dashboard - First Year New Standard License (LEGACY) (deleted) | G767: Additional license Pro-rated license : 5/20/19 - 12/14/19 | H767: 4110 Digital Signage:Dashboard Licenses | J767: 1 | K767: 198.88 | L767: 198.88 | M767: 1749519.6
... B916: Int'l Assoc. of Women in Fire & Emergency Services (MN) | C916: 07/02/2019 | D916: Invoice | E916: 1445 | F916: Website Packages:Hosting & Support:Hosting & Support | G916: WomeninFire.org website hosting and support for 2019, including site updates and event website component support. All hosting includes Wordpress updates, plugin updates, security, caching/CDN, daily backups, support system access. | H916: 4902 Websites:Website Hosting/Support | J916: 12 | K916: 300 | L916: 3600 | M916: 1911021.6
B917: Fort Mitchell (KY) Fire Department | C917: 07/03/2019 | D917: Invoice | E917: 1455 | F917: Dashboards:Dashboard Renewal - Annual License Renewal - PSIN Launch Client | G917: PSIN (now First Arriving) Digital Dashboard License Renewal - Sep 01 2019-Aug 31 2020 (2 Devices) | H917: 4110 Digital Signage:Dashboard Licenses | J917: 0 | L917: 0 | M917: 1911021.6
B918: Fire Apparatus Manufacturers Association (FAMA) (FL) | C918: 07/03/2019 | D918: Invoice | E918: 1446 | F918: Marketing Services:Design & Production | G918: Design & Pre-Press Production for Summer 2019 FEMSA/FAMA Newsletter (50% of total, balance billed to FEMSA) | H918: 4302 Marketing Services:Design & Production | J918: 1 | K918: 1750 | L918: 1750 | M918: 1912771.6
B919: Fire & Emergency Manufacturers & Services Association (FEMSA) | C919: 07/03/2019 | D919: Invoice | E919: 1447 | F919: Marketing Services:Design & Production | G919: Design & Pre-Press Production for Summer 2019 FEMSA/FAMA Newsletter (50% of total, balance billed to FAMA) | H919: 4302 Marketing Services:Design & Production | J919: 1 | K919: 1750 | L919: 1750 | M919: 1914521.6
B920: Madison (OH) Fire District | C920: 07/04/2019 | D920: Invoice | E920: 1452 | F920: Dashboards:Dashboard - First Year New Standard License (LEGACY) (deleted) | G920: Annual Licenses for First Arriving Dashboard Service (renews annually due on anniversary of deployment) | H920: 4110 Digital Signage:Dashboard Licenses | J920: 2 | K920: 349 | L920: 698 | M920: 1915219.6
B921: North Richland Hills (TX) Police Department | C921: 07/04/2019 | D921: Invoice | E921: 1448 | F921: Dashboards:Dashboard - Hardware Device Deployment | G921: Pre-Loaded Chromebox with First Arriving Dashboard services (including shipping) | H921: 4103 Digital Signage:Dashboard Hardware/Deployment | J921: 3 | K921: 279 | L921: 837 | M921: 1916056.6
B922: Chagrin Valley (OH) Dispatch | C922: 07/04/2019 | D922: Invoice | E922: 1450 | F922: Dashboards:Dashboard - First Year New Standard License (LEGACY) (deleted) | G922: Pro-rated license, 8/1/19-2/29/2020 | H922: 4110 Digital Signage:Dashboard Licenses | J922: 1 | K922: 202 | L922: 202 | M922: 1916258.6
B923: Chagrin Valley (OH) Dispatch | C923: 07/04/2019 | D923: Invoice | E923: 1449 | F923: Dashboards:Dashboard - First Year New Standard License (LEGACY) (deleted) | G923: Pro-rated license, 8/1/19-2/29/2020 | H923: 4110 Digital Signage:Dashboard Licenses | J923: 1 | K923: 202 | L923: 202 | M923: 1916460.6
B924: North Richland Hills (TX) Police Department | C924: 07/04/2019 | D924: Invoice | E924: 1448 | F924: Dashboards:Dashboard - First Year New Standard License (LEGACY) (deleted) | G924: Annual Licenses for First Arriving Dashboard Service (renews annually due on anniversary of deployment) | H924: 4110 Digital Signage:Dashboard Licenses | J924: 3 | K924: 349 | L924: 1047 | M924: 1917507.6
B925: Madison (OH) Fire District | C925: 07/04/2019 | D925: Invoice | E925: 1452 | F925: Dashboards:Dashboard STANDARD Setup | G925: First Arriving Dashboard setup (onetime) | H925: 4130 Digital Signage:Dashboard Setup Fees | J925: 1 | K925: 595 | L925: 595 | M925: 1918102.6
...

Sheet Anonymizer
A2: Customer from QB | B2: Customer | D2: Product/Service per QB | E2: Product/Service | F2: Dashboard Subscription | G2: Set Up | H2: Hardware | I2: Website Hosting / Support Subscription? | J2: Website Professional Services | K2: LLC Item
A3: {=_xlfn._xlws.SORT(_xlfn.UNIQUE('Sales by Customer Detail'!B6:B5761))} -> ​Cochran (PA) Hose Fire Department | B3: Customer 1 | D3: {=_xlfn._xlws.SORT(_xlfn.UNIQUE('Sales by Customer Detail'!F6:F5761))} -> Central County MO Fire Rescue - 1 Additional License - 042020 (deleted) | E3: Prod/Svc1 | F3: =IF(VLOOKUP(D3,[1]List!$A$3:$G$100,2,FALSE)=0,"",VLOOKUP(D3,[1]List!$A$3:$G$100,2,FALSE)) -> yes | G3: =IF(VLOOKUP(D3,[1]List!$A$3:$G$100,3,FALSE)=0,"",VLOOKUP(D3,[1]List!$A$3:$G$100,3,FALSE)) | H3: =IF(VLOOKUP(D3,[1]List!$A$3:$G$100,4,FALSE)=0,"",VLOOKUP(D3,[1]List!$A$3:$G$100,4,FALSE)) | I3: =IF(VLOOKUP(D3,[1]List!$A$3:$G$100,5,FALSE)=0,"",VLOOKUP(D3,[1]List!$A$3:$G$100,5,FALSE)) | J3: =IF(VLOOKUP(D3,[1]List!$A$3:$G$100,6,FALSE)=0,"",VLOOKUP(D3,[1]List!$A$3:$G$100,6,FALSE)) | K3: =IF(VLOOKUP(D3,[1]List!$A$3:$G$100,7,FALSE)=0,"",VLOOKUP(D3,[1]List!$A$3:$G$100,7,FALSE))
A4: ​Cochran (PA) Hose Fire Department:Cochran (PA) Hose Fire Department -Enhanced Website Package-FY22-March | B4: Customer 2 | D4: Coaldale & District Emergency Services - 1 Dashboard - 042220 (deleted) | E4: Prod/Svc2 | F4: =IF(VLOOKUP(D4,[1]List!$A$3:$G$100,2,FALSE)=0,"",VLOOKUP(D4,[1]List!$A$3:$G$100,2,FALSE)) -> yes | G4: =IF(VLOOKUP(D4,[1]List!$A$3:$G$100,3,FALSE)=0,"",VLOOKUP(D4,[1]List!$A$3:$G$100,3,FALSE)) | H4: =IF(VLOOKUP(D4,[1]List!$A$3:$G$100,4,FALSE)=0,"",VLOOKUP(D4,[1]List!$A$3:$G$100,4,FALSE)) | I4: =IF(VLOOKUP(D4,[1]List!$A$3:$G$100,5,FALSE)=0,"",VLOOKUP(D4,[1]List!$A$3:$G$100,5,FALSE)) | J4: =IF(VLOOKUP(D4,[1]List!$A$3:$G$100,6,FALSE)=0,"",VLOOKUP(D4,[1]List!$A$3:$G$100,6,FALSE)) | K4: =IF(VLOOKUP(D4,[1]List!$A$3:$G$100,7,FALSE)=0,"",VLOOKUP(D4,[1]List!$A$3:$G$100,7,FALSE))
A5: ​Genesee County (NY) Emergency Management Services:​Batavia (NY) Fire Department, Town of (Genesee County) | B5: Customer 3 | D5: Consulting Services - Fire/EMS Departments | E5: Prod/Svc3 | F5: =IF(VLOOKUP(D5,[1]List!$A$3:$G$100,2,FALSE)=0,"",VLOOKUP(D5,[1]List!$A$3:$G$100,2,FALSE)) | G5: =IF(VLOOKUP(D5,[1]List!$A$3:$G$100,3,FALSE)=0,"",VLOOKUP(D5,[1]List!$A$3:$G$100,3,FALSE)) | H5: =IF(VLOOKUP(D5,[1]List!$A$3:$G$100,4,FALSE)=0,"",VLOOKUP(D5,[1]List!$A$3:$G$100,4,FALSE)) | I5: =IF(VLOOKUP(D5,[1]List!$A$3:$G$100,5,FALSE)=0,"",VLOOKUP(D5,[1]List!$A$3:$G$100,5,FALSE)) | J5: =IF(VLOOKUP(D5,[1]List!$A$3:$G$100,6,FALSE)=0,"",VLOOKUP(D5,[1]List!$A$3:$G$100,6,FALSE)) | K5: =IF(VLOOKUP(D5,[1]List!$A$3:$G$100,7,FALSE)=0,"",VLOOKUP(D5,[1]List!$A$3:$G$100,7,FALSE)) -> yes
A6: ​Genesee County (NY) Emergency Management Services:​Elba (NY) Volunteer Fire Department (Genesee County) | B6: Customer 4 | D6: Customer Referral Discount | E6: Prod/Svc4 | F6: =IF(VLOOKUP(D6,[1]List!$A$3:$G$100,2,FALSE)=0,"",VLOOKUP(D6,[1]List!$A$3:$G$100,2,FALSE)) | G6: =IF(VLOOKUP(D6,[1]List!$A$3:$G$100,3,FALSE)=0,"",VLOOKUP(D6,[1]List!$A$3:$G$100,3,FALSE)) | H6: =IF(VLOOKUP(D6,[1]List!$A$3:$G$100,4,FALSE)=0,"",VLOOKUP(D6,[1]List!$A$3:$G$100,4,FALSE)) | I6: =IF(VLOOKUP(D6,[1]List!$A$3:$G$100,5,FALSE)=0,"",VLOOKUP(D6,[1]List!$A$3:$G$100,5,FALSE)) | J6: =IF(VLOOKUP(D6,[1]List!$A$3:$G$100,6,FALSE)=0,"",VLOOKUP(D6,[1]List!$A$3:$G$100,6,FALSE)) | K6: =IF(VLOOKUP(D6,[1]List!$A$3:$G$100,7,FALSE)=0,"",VLOOKUP(D6,[1]List!$A$3:$G$100,7,FALSE)) -> yes
A7: ​Genesee County (NY) Emergency Management Services:​LeRoy (NY) Fire Department (Genesee County) | B7: Customer 5 | D7: Dashboard BASIC Setup | E7: Prod/Svc5 | F7: =IF(VLOOKUP(D7,[1]List!$A$3:$G$100,2,FALSE)=0,"",VLOOKUP(D7,[1]List!$A$3:$G$100,2,FALSE)) | G7: =IF(VLOOKUP(D7,[1]List!$A$3:$G$100,3,FALSE)=0,"",VLOOKUP(D7,[1]List!$A$3:$G$100,3,FALSE)) -> yes | H7: =IF(VLOOKUP(D7,[1]List!$A$3:$G$100,4,FALSE)=0,"",VLOOKUP(D7,[1]List!$A$3:$G$100,4,FALSE)) | I7: =IF(VLOOKUP(D7,[1]List!$A$3:$G$100,5,FALSE)=0,"",VLOOKUP(D7,[1]List!$A$3:$G$100,5,FALSE)) | J7: =IF(VLOOKUP(D7,[1]List!$A$3:$G$100,6,FALSE)=0,"",VLOOKUP(D7,[1]List!$A$3:$G$100,6,FALSE)) | K7: =IF(VLOOKUP(D7,[1]List!$A$3:$G$100,7,FALSE)=0,"",VLOOKUP(D7,[1]List!$A$3:$G$100,7,FALSE))
A8: ​Genesee County (NY) Emergency Management Services:​Oakfield (NY) Fire Department (Genesee County) | B8: Customer 6 | D8: Dashboards:Dashboard - 2-Year Standard Subscription (deleted) | E8: Prod/Svc6 | F8: =IF(VLOOKUP(D8,[1]List!$A$3:$G$100,2,FALSE)=0,"",VLOOKUP(D8,[1]List!$A$3:$G$100,2,FALSE)) -> yes | G8: =IF(VLOOKUP(D8,[1]List!$A$3:$G$100,3,FALSE)=0,"",VLOOKUP(D8,[1]List!$A$3:$G$100,3,FALSE)) | H8: =IF(VLOOKUP(D8,[1]List!$A$3:$G$100,4,FALSE)=0,"",VLOOKUP(D8,[1]List!$A$3:$G$100,4,FALSE)) | I8: =IF(VLOOKUP(D8,[1]List!$A$3:$G$100,5,FALSE)=0,"",VLOOKUP(D8,[1]List!$A$3:$G$100,5,FALSE)) | J8: =IF(VLOOKUP(D8,[1]List!$A$3:$G$100,6,FALSE)=0,"",VLOOKUP(D8,[1]List!$A$3:$G$100,6,FALSE)) | K8: =IF(VLOOKUP(D8,[1]List!$A$3:$G$100,7,FALSE)=0,"",VLOOKUP(D8,[1]List!$A$3:$G$100,7,FALSE))
A9: ​Genesee County (NY) Emergency Management Services:Batavia (NY) Fire Department, ​City of (Genesee County) | B9: Customer 7 | D9: Dashboards:Dashboard - 3-Year Standard Subscription (deleted) | E9: Prod/Svc7 | F9: =IF(VLOOKUP(D9,[1]List!$A$3:$G$100,2,FALSE)=0,"",VLOOKUP(D9,[1]List!$A$3:$G$100,2,FALSE)) -> yes | G9: =IF(VLOOKUP(D9,[1]List!$A$3:$G$100,3,FALSE)=0,"",VLOOKUP(D9,[1]List!$A$3:$G$100,3,FALSE)) | H9: =IF(VLOOKUP(D9,[1]List!$A$3:$G$100,4,FALSE)=0,"",VLOOKUP(D9,[1]List!$A$3:$G$100,4,FALSE)) | I9: =IF(VLOOKUP(D9,[1]List!$A$3:$G$100,5,FALSE)=0,"",VLOOKUP(D9,[1]List!$A$3:$G$100,5,FALSE)) | J9: =IF(VLOOKUP(D9,[1]List!$A$3:$G$100,6,FALSE)=0,"",VLOOKUP(D9,[1]List!$A$3:$G$100,6,FALSE)) | K9: =IF(VLOOKUP(D9,[1]List!$A$3:$G$100,7,FALSE)=0,"",VLOOKUP(D9,[1]List!$A$3:$G$100,7,FALSE))
A10: ​Genesee County (NY) Emergency Management Services:Bethany (NY) Volunteer Fire Department (Genesee County) | B10: Customer 8 | D10: Dashboards:Dashboard - 4-Year Standard Subscription (deleted) | E10: Prod/Svc8 | F10: =IF(VLOOKUP(D10,[1]List!$A$3:$G$100,2,FALSE)=0,"",VLOOKUP(D10,[1]List!$A$3:$G$100,2,FALSE)) -> yes | G10: =IF(VLOOKUP(D10,[1]List!$A$3:$G$100,3,FALSE)=0,"",VLOOKUP(D10,[1]List!$A$3:$G$100,3,FALSE)) | H10: =IF(VLOOKUP(D10,[1]List!$A$3:$G$100,4,FALSE)=0,"",VLOOKUP(D10,[1]List!$A$3:$G$100,4,FALSE)) | I10: =IF(VLOOKUP(D10,[1]List!$A$3:$G$100,5,FALSE)=0,"",VLOOKUP(D10,[1]List!$A$3:$G$100,5,FALSE)) | J10: =IF(VLOOKUP(D10,[1]List!$A$3:$G$100,6,FALSE)=0,"",VLOOKUP(D10,[1]List!$A$3:$G$100,6,FALSE)) | K10: =IF(VLOOKUP(D10,[1]List!$A$3:$G$100,7,FALSE)=0,"",VLOOKUP(D10,[1]List!$A$3:$G$100,7,FALSE))
A11: ​Genesee County (NY) Emergency Management Services:Byron (NY) Fire Department (Genesee County) | B11: Customer 9 | D11: Dashboards:Dashboard - First Year New Basic License (deleted) | E11: Prod/Svc9 | F11: =IF(VLOOKUP(D11,[1]List!$A$3:$G$100,2,FALSE)=0,"",VLOOKUP(D11,[1]List!$A$3:$G$100,2,FALSE)) -> yes | G11: =IF(VLOOKUP(D11,[1]List!$A$3:$G$100,3,FALSE)=0,"",VLOOKUP(D11,[1]List!$A$3:$G$100,3,FALSE)) | H11: =IF(VLOOKUP(D11,[1]List!$A$3:$G$100,4,FALSE)=0,"",VLOOKUP(D11,[1]List!$A$3:$G$100,4,FALSE)) | I11: =IF(VLOOKUP(D11,[1]List!$A$3:$G$100,5,FALSE)=0,"",VLOOKUP(D11,[1]List!$A$3:$G$100,5,FALSE)) | J11: =IF(VLOOKUP(D11,[1]List!$A$3:$G$100,6,FALSE)=0,"",VLOOKUP(D11,[1]List!$A$3:$G$100,6,FALSE)) | K11: =IF(VLOOKUP(D11,[1]List!$A$3:$G$100,7,FALSE)=0,"",VLOOKUP(D11,[1]List!$A$3:$G$100,7,FALSE))
A12: ​Genesee County (NY) Emergency Management Services:Corfu (NY) Fire Department (Genesee County) | B12: Customer 10 | D12: Dashboards:Dashboard - First Year New Desktop/Tablet License (LEGACY) (deleted) | E12: Prod/Svc10 | F12: =IF(VLOOKUP(D12,[1]List!$A$3:$G$100,2,FALSE)=0,"",VLOOKUP(D12,[1]List!$A$3:$G$100,2,FALSE)) -> yes | G12: =IF(VLOOKUP(D12,[1]List!$A$3:$G$100,3,FALSE)=0,"",VLOOKUP(D12,[1]List!$A$3:$G$100,3,FALSE)) | H12: =IF(VLOOKUP(D12,[1]List!$A$3:$G$100,4,FALSE)=0,"",VLOOKUP(D12,[1]List!$A$3:$G$100,4,FALSE)) | I12: =IF(VLOOKUP(D12,[1]List!$A$3:$G$100,5,FALSE)=0,"",VLOOKUP(D12,[1]List!$A$3:$G$100,5,FALSE)) | J12: =IF(VLOOKUP(D12,[1]List!$A$3:$G$100,6,FALSE)=0,"",VLOOKUP(D12,[1]List!$A$3:$G$100,6,FALSE)) | K12: =IF(VLOOKUP(D12,[1]List!$A$3:$G$100,7,FALSE)=0,"",VLOOKUP(D12,[1]List!$A$3:$G$100,7,FALSE))
A13: ​Genesee County (NY) Emergency Management Services:Genesee County (NY) Emergency Management Services - Enterprise 2022 | B13: Customer 11 | D13: Dashboards:Dashboard - First Year New Standard License (LEGACY) (deleted) | E13: Prod/Svc11 | F13: =IF(VLOOKUP(D13,[1]List!$A$3:$G$100,2,FALSE)=0,"",VLOOKUP(D13,[1]List!$A$3:$G$100,2,FALSE)) -> yes | G13: =IF(VLOOKUP(D13,[1]List!$A$3:$G$100,3,FALSE)=0,"",VLOOKUP(D13,[1]List!$A$3:$G$100,3,FALSE)) | H13: =IF(VLOOKUP(D13,[1]List!$A$3:$G$100,4,FALSE)=0,"",VLOOKUP(D13,[1]List!$A$3:$G$100,4,FALSE)) | I13: =IF(VLOOKUP(D13,[1]List!$A$3:$G$100,5,FALSE)=0,"",VLOOKUP(D13,[1]List!$A$3:$G$100,5,FALSE)) | J13: =IF(VLOOKUP(D13,[1]List!$A$3:$G$100,6,FALSE)=0,"",VLOOKUP(D13,[1]List!$A$3:$G$100,6,FALSE)) | K13: =IF(VLOOKUP(D13,[1]List!$A$3:$G$100,7,FALSE)=0,"",VLOOKUP(D13,[1]List!$A$3:$G$100,7,FALSE))
A14: #1 Green Township (IN) Volunteer Fire Department | B14: Customer 12 | D14: Dashboards:Dashboard - Hardware (deleted) | E14: Prod/Svc12 | F14: =IF(VLOOKUP(D14,[1]List!$A$3:$G$100,2,FALSE)=0,"",VLOOKUP(D14,[1]List!$A$3:$G$100,2,FALSE)) -> yes | G14: =IF(VLOOKUP(D14,[1]List!$A$3:$G$100,3,FALSE)=0,"",VLOOKUP(D14,[1]List!$A$3:$G$100,3,FALSE)) | H14: =IF(VLOOKUP(D14,[1]List!$A$3:$G$100,4,FALSE)=0,"",VLOOKUP(D14,[1]List!$A$3:$G$100,4,FALSE)) | I14: =IF(VLOOKUP(D14,[1]List!$A$3:$G$100,5,FALSE)=0,"",VLOOKUP(D14,[1]List!$A$3:$G$100,5,FALSE)) | J14: =IF(VLOOKUP(D14,[1]List!$A$3:$G$100,6,FALSE)=0,"",VLOOKUP(D14,[1]List!$A$3:$G$100,6,FALSE)) | K14: =IF(VLOOKUP(D14,[1]List!$A$3:$G$100,7,FALSE)=0,"",VLOOKUP(D14,[1]List!$A$3:$G$100,7,FALSE))
A15: Abbeville County (SC) Emergency Services | B15: Customer 13 | D15: Dashboards:Dashboard - Hardware Device Deployment | E15: Prod/Svc13 | F15: =IF(VLOOKUP(D15,[1]List!$A$3:$G$100,2,FALSE)=0,"",VLOOKUP(D15,[1]List!$A$3:$G$100,2,FALSE)) | G15: =IF(VLOOKUP(D15,[1]List!$A$3:$G$100,3,FALSE)=0,"",VLOOKUP(D15,[1]List!$A$3:$G$100,3,FALSE)) | H15: =IF(VLOOKUP(D15,[1]List!$A$3:$G$100,4,FALSE)=0,"",VLOOKUP(D15,[1]List!$A$3:$G$100,4,FALSE)) -> yes | I15: =IF(VLOOKUP(D15,[1]List!$A$3:$G$100,5,FALSE)=0,"",VLOOKUP(D15,[1]List!$A$3:$G$100,5,FALSE)) | J15: =IF(VLOOKUP(D15,[1]List!$A$3:$G$100,6,FALSE)=0,"",VLOOKUP(D15,[1]List!$A$3:$G$100,6,FALSE)) | K15: =IF(VLOOKUP(D15,[1]List!$A$3:$G$100,7,FALSE)=0,"",VLOOKUP(D15,[1]List!$A$3:$G$100,7,FALSE))
... A86: Bloomington (IN) Fire Department | B86: Customer 84 | D86: Wilder KY FD - 1 Chromebox and License - 043020 (deleted) | E86: Prod/Svc84 | F86: =IF(VLOOKUP(D86,[1]List!$A$3:$G$100,2,FALSE)=0,"",VLOOKUP(D86,[1]List!$A$3:$G$100,2,FALSE)) -> yes | G86: =IF(VLOOKUP(D86,[1]List!$A$3:$G$100,3,FALSE)=0,"",VLOOKUP(D86,[1]List!$A$3:$G$100,3,FALSE)) | H86: =IF(VLOOKUP(D86,[1]List!$A$3:$G$100,4,FALSE)=0,"",VLOOKUP(D86,[1]List!$A$3:$G$100,4,FALSE)) | I86: =IF(VLOOKUP(D86,[1]List!$A$3:$G$100,5,FALSE)=0,"",VLOOKUP(D86,[1]List!$A$3:$G$100,5,FALSE)) | J86: =IF(VLOOKUP(D86,[1]List!$A$3:$G$100,6,FALSE)=0,"",VLOOKUP(D86,[1]List!$A$3:$G$100,6,FALSE)) | K86: =IF(VLOOKUP(D86,[1]List!$A$3:$G$100,7,FALSE)=0,"",VLOOKUP(D86,[1]List!$A$3:$G$100,7,FALSE))
A87: Blue Ridge (NC) Fire & Rescue | B87: Customer 85 | D87: 0
A88: Boca Raton (FL) Fire Rescue | B88: Customer 86
A89: Boca Raton (FL) Govt., City of | B89: Customer 87
A90: Bon Air (PA) Fire Company | B90: Customer 88
A91: Bonita Springs (FL) Fire Control and Rescue District | B91: Customer 89
A92: Bonner Springs (KS) Fire-EMS | B92: Customer 90
A93: Boone County (KY) Fire | B93: Customer 91
A94: Boonsboro (VA) Fire & Rescue | B94: Customer 92
A95: Boonton (NJ) Fire Department | B95: Customer 93
A96: Borough of Bellefonte (PA):Bellefonte (PA) Recruitment Project | B96: Customer 94
A97: Borough of Northvale (NJ) Fire Department | B97: Customer 95
A98: Borough of Northvale (NJ) Fire Department:Northvale (NJ) Fire Department-Standard Web Package-FY21-December | B98: Customer 96
A99: Botetourt County (VA) Fire & EMS | B99: Customer 97
... A993: Zionsville (IN) Fire Department | B993: Customer 991
B994: Customer 992
B995: Customer 993
B996: Customer 994

Sheet Sales by Cust Detail External
B2: Customer | C2: Date | D2: Transaction Type | E2: Num | F2: Product/Service | G2: Memo/Description | H2: Qty | I2: Sales Price | J2: Amount | K2: Subscription Start Date | L2: Subscription End Date
B3: =VLOOKUP('Sales by Customer Detail'!B6,Anonymizer!$A$3:$B$996,2,FALSE) -> Customer 564 | C3: ='Sales by Customer Detail'!C6 -> 01/02/2018 | D3: ='Sales by Customer Detail'!D6 -> Invoice | E3: ='Sales by Customer Detail'!E6 -> 1014 | F3: =VLOOKUP('Sales by Customer Detail'!F6,Anonymizer!$D$3:$E$86,2,FALSE) -> Prod/Svc70 | G3: memo | H3: ='Sales by Customer Detail'!J6 -> 1 | I3: ='Sales by Customer Detail'!K6 -> 30000 | J3: ='Sales by Customer Detail'!L6 -> 30000 | K3: ='Sales by Customer Detail'!N6 -> 0 | L3: ='Sales by Customer Detail'!O6 -> 0
B4: =VLOOKUP('Sales by Customer Detail'!B7,Anonymizer!$A$3:$B$996,2,FALSE) -> Customer 620 | C4: ='Sales by Customer Detail'!C7 -> 01/03/2018 | D4: ='Sales by Customer Detail'!D7 -> Invoice | E4: ='Sales by Customer Detail'!E7 -> 1016 | F4: =VLOOKUP('Sales by Customer Detail'!F7,Anonymizer!$D$3:$E$86,2,FALSE) -> Prod/Svc77 | G4: memo | H4: ='Sales by Customer Detail'!J7 -> 4 | I4: ='Sales by Customer Detail'!K7 -> 150 | J4: ='Sales by Customer Detail'!L7 -> 600 | K4: ='Sales by Customer Detail'!N7 -> 0 | L4: ='Sales by Customer Detail'!O7 -> 0
B5: =VLOOKUP('Sales by Customer Detail'!B8,Anonymizer!$A$3:$B$996,2,FALSE) -> Customer 35 | C5: ='Sales by Customer Detail'!C8 -> 01/03/2018 | D5: ='Sales by Customer Detail'!D8 -> Invoice | E5: ='Sales by Customer Detail'!E8 -> 1017 | F5: =VLOOKUP('Sales by Customer Detail'!F8,Anonymizer!$D$3:$E$86,2,FALSE) -> Prod/Svc77 | G5: memo | H5: ='Sales by Customer Detail'!J8 -> 1 | I5: ='Sales by Customer Detail'!K8 -> -35 | J5: ='Sales by Customer Detail'!L8 -> -35 | K5: ='Sales by Customer Detail'!N8 -> 0 | L5: ='Sales by Customer Detail'!O8 -> 0
B6: =VLOOKUP('Sales by Customer Detail'!B9,Anonymizer!$A$3:$B$996,2,FALSE) -> Customer 35 | C6: ='Sales by Customer Detail'!C9 -> 01/03/2018 | D6: ='Sales by Customer Detail'!D9 -> Invoice | E6: ='Sales by Customer Detail'!E9 -> 1017 | F6: =VLOOKUP('Sales by Customer Detail'!F9,Anonymizer!$D$3:$E$86,2,FALSE) -> Prod/Svc77 | G6: memo | H6: ='Sales by Customer Detail'!J9 -> 12 | I6: ='Sales by Customer Detail'!K9 -> 29 | J6: ='Sales by Customer Detail'!L9 -> 348 | K6: ='Sales by Customer Detail'!N9 -> 0 | L6: ='Sales by Customer Detail'!O9 -> 0
B7: =VLOOKUP('Sales by Customer Detail'!B10,Anonymizer!$A$3:$B$996,2,FALSE) -> Customer 328 | C7: ='Sales by Customer Detail'!C10 -> 01/03/2018 | D7: ='Sales by Customer Detail'!D10 -> Invoice | E7: ='Sales by Customer Detail'!E10 -> 1018 | F7: =VLOOKUP('Sales by Customer Detail'!F10,Anonymizer!$D$3:$E$86,2,FALSE) -> Prod/Svc77 | G7: memo | H7: ='Sales by Customer Detail'!J10 -> 12 | I7: ='Sales by Customer Detail'!K10 -> 49 | J7: ='Sales by Customer Detail'!L10 -> 588 | K7: ='Sales by Customer Detail'!N10 -> 0 | L7: ='Sales by Customer Detail'!O10 -> 0
B8: =VLOOKUP('Sales by Customer Detail'!B11,Anonymizer!$A$3:$B$996,2,FALSE) -> Customer 620 | C8: ='Sales by Customer Detail'!C11 -> 01/03/2018 | D8: ='Sales by Customer Detail'!D11 -> Invoice | E8: ='Sales by Customer Detail'!E11 -> 1016 | F8: =VLOOKUP('Sales by Customer Detail'!F11,Anonymizer!$D$3:$E$86,2,FALSE) -> Prod/Svc77 | G8: memo | H8: ='Sales by Customer Detail'!J11 -> 12 | I8: ='Sales by Customer Detail'!K11 -> 150 | J8: ='Sales by Customer Detail'!L11 -> 1800 | K8: ='Sales by Customer Detail'!N11 -> 0 | L8: ='Sales by Customer Detail'!O11 -> 0
B9: =VLOOKUP('Sales by Customer Detail'!B12,Anonymizer!$A$3:$B$996,2,FALSE) -> Customer 328 | C9: ='Sales by Customer Detail'!C12 -> 01/03/2018 | D9: ='Sales by Customer Detail'!D12 -> Invoice | E9: ='Sales by Customer Detail'!E12 -> 1018 | F9: =VLOOKUP('Sales by Customer Detail'!F12,Anonymizer!$D$3:$E$86,2,FALSE) -> Prod/Svc77 | G9: memo | H9: ='Sales by Customer Detail'!J12 -> 1 | I9: ='Sales by Customer Detail'!K12 -> -58.8 | J9: ='Sales by Customer Detail'!L12 -> -58.8 | K9: ='Sales by Customer Detail'!N12 -> 0 | L9: ='Sales by Customer Detail'!O12 -> 0
B10: =VLOOKUP('Sales by Customer Detail'!B13,Anonymizer!$A$3:$B$996,2,FALSE) -> Customer 620 | C10: ='Sales by Customer Detail'!C13 -> 01/03/2018 | D10: ='Sales by Customer Detail'!D13 -> Invoice | E10: ='Sales by Customer Detail'!E13 -> 1016 | F10: =VLOOKUP('Sales by Customer Detail'!F13,Anonymizer!$D$3:$E$86,2,FALSE) -> Prod/Svc77 | G10: memo | H10: ='Sales by Customer Detail'!J13 -> 1 | I10: ='Sales by Customer Detail'!K13 -> -240 | J10: ='Sales by Customer Detail'!L13 -> -240 | K10: ='Sales by Customer Detail'!N13 -> 0 | L10: ='Sales by Customer Detail'!O13 -> 0
B11: =VLOOKUP('Sales by Customer Detail'!B14,Anonymizer!$A$3:$B$996,2,FALSE) -> Customer 811 | C11: ='Sales by Customer Detail'!C14 -> 01/18/2018 | D11: ='Sales by Customer Detail'!D14 -> Invoice | E11: ='Sales by Customer Detail'!E14 -> 1019 | F11: =VLOOKUP('Sales by Customer Detail'!F14,Anonymizer!$D$3:$E$86,2,FALSE) -> Prod/Svc66 | G11: memo | H11: ='Sales by Customer Detail'!J14 -> 1 | I11: ='Sales by Customer Detail'!K14 -> 40000 | J11: ='Sales by Customer Detail'!L14 -> 40000 | K11: ='Sales by Customer Detail'!N14 -> 0 | L11: ='Sales by Customer Detail'!O14 -> 0
B12: =VLOOKUP('Sales by Customer Detail'!B15,Anonymizer!$A$3:$B$996,2,FALSE) -> Customer 67 | C12: ='Sales by Customer Detail'!C15 -> 01/31/2018 | D12: ='Sales by Customer Detail'!D15 -> Invoice | E12: ='Sales by Customer Detail'!E15 -> 1020 | F12: =VLOOKUP('Sales by Customer Detail'!F15,Anonymizer!$D$3:$E$86,2,FALSE) -> Prod/Svc77 | G12: memo | H12: ='Sales by Customer Detail'!J15 -> 24 | I12: ='Sales by Customer Detail'!K15 -> 59 | J12: ='Sales by Customer Detail'!L15 -> 1416 | K12: ='Sales by Customer Detail'!N15 -> 0 | L12: ='Sales by Customer Detail'!O15 -> 0
B13: =VLOOKUP('Sales by Customer Detail'!B16,Anonymizer!$A$3:$B$996,2,FALSE) -> Customer 67 | C13: ='Sales by Customer Detail'!C16 -> 01/31/2018 | D13: ='Sales by Customer Detail'!D16 -> Invoice | E13: ='Sales by Customer Detail'!E16 -> 1020 | F13: =VLOOKUP('Sales by Customer Detail'!F16,Anonymizer!$D$3:$E$86,2,FALSE) -> Prod/Svc73 | G13: memo | H13: ='Sales by Customer Detail'!J16 -> 1 | I13: ='Sales by Customer Detail'!K16 -> 3495 | J13: ='Sales by Customer Detail'!L16 -> 3495 | K13: ='Sales by Customer Detail'!N16 -> 0 | L13: ='Sales by Customer Detail'!O16 -> 0
B14: =VLOOKUP('Sales by Customer Detail'!B17,Anonymizer!$A$3:$B$996,2,FALSE) -> Customer 762 | C14: ='Sales by Customer Detail'!C17 -> 01/31/2018 | D14: ='Sales by Customer Detail'!D17 -> Invoice | E14: ='Sales by Customer Detail'!E17 -> 1021 | F14: =VLOOKUP('Sales by Customer Detail'!F17,Anonymizer!$D$3:$E$86,2,FALSE) -> Prod/Svc73 | G14: memo | H14: ='Sales by Customer Detail'!J17 -> 1 | I14: ='Sales by Customer Detail'!K17 -> 0 | J14: ='Sales by Customer Detail'!L17 -> 0 | K14: ='Sales by Customer Detail'!N17 -> 0 | L14: ='Sales by Customer Detail'!O17 -> 0
... B5758: =VLOOKUP('Sales by Customer Detail'!B5761,Anonymizer!$A$3:$B$996,2,FALSE) -> Customer 730 | C5758: ='Sales by Customer Detail'!C5761 -> 04/29/2022 | D5758: ='Sales by Customer Detail'!D5761 -> Invoice | E5758: ='Sales by Customer Detail'!E5761 -> 3969 | F5758: =VLOOKUP('Sales by Customer Detail'!F5761,Anonymizer!$D$3:$E$86,2,FALSE) -> Prod/Svc13 | G5758: memo | H5758: ='Sales by Customer Detail'!J5761 -> 1 | I5758: ='Sales by Customer Detail'!K5761 -> 299 | J5758: ='Sales by Customer Detail'!L5761 -> 299 | K5758: ='Sales by Customer Detail'!N5761 -> 05/20/2022 | L5758: ='Sales by Customer Detail'!O5761 -> 11/25/2022

Sheet ProdSvc mapping to revenue type
A1: Product/Service | B1: Dashboard Subscription | C1: Set Up | D1: Hardware | E1: Website Hosting / Support Subscription? | F1: Website Professional Services | G1: LLC Item
A2: Prod/Svc1 | B2: yes
A3: Prod/Svc2 | B3: yes
A4: Prod/Svc3 | G4: yes
A5: Prod/Svc4 | G5: yes
A6: Prod/Svc5 | C6: yes
A7: Prod/Svc6 | B7: yes
A8: Prod/Svc7 | B8: yes
A9: Prod/Svc8 | B9: yes
A10: Prod/Svc9 | B10: yes
A11: Prod/Svc10 | B11: yes
A12: Prod/Svc11 | B12: yes
A13: Prod/Svc12 | B13: yes
A14: Prod/Svc13 | D14: yes
A15: Prod/Svc14 | B15: yes
A16: Prod/Svc15 | C16: yes
A17: Prod/Svc16 | B17: yes
A18: Prod/Svc17 | C18: yes
A19: Prod/Svc18 | B19: yes
A20: Prod/Svc19 | B20: yes
A21: Prod/Svc20 | C21: yes
A22: Prod/Svc21 | B22: yes
A23: Prod/Svc22 | B23: yes
A24: Prod/Svc23 | C24: yes
A25: Prod/Svc24 | B25: yes
A26: Prod/Svc25 | B26: yes
A27: Prod/Svc26 | B27: yes
A28: Prod/Svc27 | B28: yes
A29: Prod/Svc28 | B29: yes
A30: Prod/Svc29 | B30: yes
A31: Prod/Svc30 | B31: yes
A32: Prod/Svc31 | B32: yes
A33: Prod/Svc32 | B33: yes
A34: Prod/Svc33 | B34: yes
A35: Prod/Svc34 | B35: yes
A36: Prod/Svc35 | B36: yes
... A38: Prod/Svc37 | B38: yes
A39: Prod/Svc38 | C39: yes
A40: Prod/Svc39 | B40: yes
A41: Prod/Svc40 | C41: yes
A42: Prod/Svc41 | B42: yes
A43: Prod/Svc42 | B43: yes
A44: Prod/Svc43 | B44: yes
A45: Prod/Svc44 | B45: yes
A46: Prod/Svc45 | B46: yes
A47: Prod/Svc46 | B47: yes
A48: Prod/Svc47 | B48: yes
A49: Prod/Svc48 | B49: yes
A50: Prod/Svc49 | F50: yes
A51: Prod/Svc50 | G51: yes
A52: Prod/Svc51 | G52: yes
A53: Prod/Svc52 | G53: yes
A54: Prod/Svc53 | G54: yes
A55: Prod/Svc54 | G55: yes
A56: Prod/Svc55 | G56: yes
A57: Prod/Svc56 | G57: yes
A58: Prod/Svc57 | G58: yes
A59: Prod/Svc58 | G59: yes
A60: Prod/Svc59 | G60: yes
A61: Prod/Svc60 | G61: yes
A62: Prod/Svc61 | G62: yes
... A68: Prod/Svc67 | G68: yes
A69: Prod/Svc68 | B69: yes
A70: Prod/Svc69 | G70: yes
A71: Prod/Svc70 | G71: yes
A72: Prod/Svc71 | B72: yes
A73: Prod/Svc72 | F73: yes
A74: Prod/Svc73 | F74: yes
A75: Prod/Svc74 | F75: yes
A76: Prod/Svc75 | F76: yes
A77: Prod/Svc76 | F77: yes
A78: Prod/Svc77 | E78: yes
A79: Prod/Svc78 | E79: yes
A80: Prod/Svc79 | E80: yes
A81: Prod/Svc80 | F81: yes
A82: Prod/Svc81 | F82: yes
A83: Prod/Svc82 | F83: yes
A84: Prod/Svc83 | F84: yes
A85: Prod/Svc84 | B85: yes

Sheet Rev rec assumptions
B3: Revenue recognition period assumptions
B5: Dashboard Subscription | C5: Recognize revenue from the subscription start date to the subscription end date. If no dates, recognize revenue for one year starting at the invoice date.
B6: Set Up | C6: Recognize revenue over three years from the invoice date
B7: Hardware | C7: Regognize all revenue on the invoice date
B8: Website Hosting / Support Subscription? | C8: Recognize revenue from the subscription start date to the subscription end date. If no dates, recognize revenue for one year starting at the invoice date.
B9: Website Professional Services | C9: Regognize all revenue on the invoice date
B10: LLC Item | C10: Regognize all revenue on the invoice date
